gpt2ppl/__init__.py
gpt2ppl/demo_doc.py
gpt2ppl/demo_sent.py
gpt2ppl/gpt2ppl.py
gpt2ppl_zh-0.2.0.dist-info/METADATA
gpt2ppl_zh-0.2.0.dist-info/WHEEL
gpt2ppl_zh-0.2.0.dist-info/top_level.txt
gpt2ppl_zh-0.2.0.dist-info/RECORD
