Metadata-Version: 2.1
Name: gpt2ppl-zh
Version: 0.2.0
Summary: Chinese sentence perplexity calculation based on GPT2 pre-trained model
Home-page: https://github.com/zejunwang1/gpt2ppl-zh
Author: wangzejun
Author-email: wangzejunscut@126.com
License: MIT License
Requires-Dist: transformers
Requires-Dist: torch
